aligner_pytorch/__init__.py
aligner_pytorch/mas.py
aligner_pytorch/mas_c.cpython-39-darwin.so
aligner_pytorch-0.0.13.dist-info/LICENSE
aligner_pytorch-0.0.13.dist-info/METADATA
aligner_pytorch-0.0.13.dist-info/WHEEL
aligner_pytorch-0.0.13.dist-info/top_level.txt
aligner_pytorch-0.0.13.dist-info/RECORD
